VCry/__init__.py
VCry/vcry.py
vcry-0.1.4.dist-info/LICENSE
vcry-0.1.4.dist-info/METADATA
vcry-0.1.4.dist-info/WHEEL
vcry-0.1.4.dist-info/top_level.txt
vcry-0.1.4.dist-info/RECORD
