Metadata-Version: 2.2
Name: VCry
Version: 0.1.4
Summary: A simple library for encryption/decryption with multiple ciphers.
Home-page: https://vcom-team.netlify.app/
Author: ViniLog
Author-email: ViniLog <Xdsateam2@example.com>
License: MIT License
Project-URL: Homepage, https://vcom-team.netlify.app/
Keywords: encryption,decryption,cipher,cryptography
Classifier: Development Status :: 3 - Alpha
Classifier: Intended Audience :: Developers
Classifier: Topic :: Security :: Cryptography
Classifier: License :: OSI Approved :: MIT License
Classifier: Programming Language :: Python :: 3
Classifier: Programming Language :: Python :: 3.7
Classifier: Programming Language :: Python :: 3.8
Classifier: Programming Language :: Python :: 3.9
Classifier: Programming Language :: Python :: 3.10
Requires-Python: >=3.6
License-File: LICENSE
Dynamic: author
Dynamic: home-page
Dynamic: requires-python
